retoys-0.0.2.dist-info/licenses/LICENSE
retoys_imp/__init__.py
retoys_imp/foo.py
retoys_imp/bar/__init__.py
retoys_imp/bar/dib.py
retoys-0.0.2.dist-info/METADATA
retoys-0.0.2.dist-info/WHEEL
retoys-0.0.2.dist-info/top_level.txt
retoys-0.0.2.dist-info/RECORD
